{
  "project_info": {
    "project_number": "1071520091116",
    "project_id": "er-portal-aa0f0",
    "storage_bucket": "er-portal-aa0f0.appspot.com"
  },
  "client": [
    {
      "client_info": {
        "mobilesdk_app_id": "1:1071520091116:android:9b67c10baacb5f243c8ec9",
        "android_client_info": {
          "package_name": "com.shakshi.erp"
        }
      },
      "oauth_client": [
        {
          "client_id": "1071520091116-puu4kijl7o3pkcf0sbeokps2gfh59msv.apps.googleusercontent.com",
          "client_type": 3
        }
      ],
      "api_key": [
        {
          "current_key": "AIzaSyD6NdtPphPmHIFuwQLxBE49_FmzWqkc1Jc"
        }
      ],
      "services": {
        "appinvite_service": {
          "other_platform_oauth_client": [
            {
              "client_id": "1071520091116-puu4kijl7o3pkcf0sbeokps2gfh59msv.apps.googleusercontent.com",
              "client_type": 3
            }
          ]
        }
      }
    }
  ],
  "configuration_version": "1"
}